pytractoviz-0.4.4.dist-info/METADATA
pytractoviz-0.4.4.dist-info/WHEEL
pytractoviz-0.4.4.dist-info/entry_points.txt
pytractoviz-0.4.4.dist-info/licenses/LICENSE
pytractoviz/__init__.py
pytractoviz/__main__.py
pytractoviz/_internal/__init__.py
pytractoviz/_internal/cli.py
pytractoviz/_internal/debug.py
pytractoviz/html.py
pytractoviz/py.typed
pytractoviz/utils.py
pytractoviz/viz.py
pytractoviz-0.4.4.dist-info/RECORD
